BooPHF.h
LICENSE.txt
MANIFEST.in
Makefile
README.md
bbhash.pyx
bbhash_table.pyx
setup.py
test_bbhash.py
test_table.py
bbhash.egg-info/PKG-INFO
bbhash.egg-info/SOURCES.txt
bbhash.egg-info/dependency_links.txt
bbhash.egg-info/requires.txt
bbhash.egg-info/top_level.txt