Metadata-Version: 2.1
Name: bbhash
Version: 0.5.3
Summary: A Python wrapper for the BBHash Minimal Perfect Hash Function
Home-page: http://github.com/dib-lab/pybbhash
Author: C. Titus Brown
Author-email: titus@idyll.org
License: BSD 3-clause
Platform: UNKNOWN
